setup.py
ga_bi_distribution_classes/Binomialdistribution.py
ga_bi_distribution_classes/Gaussiandistribution.py
ga_bi_distribution_classes/Generaldistribution.py
ga_bi_distribution_classes/__init__.py
ga_bi_distribution_classes.egg-info/PKG-INFO
ga_bi_distribution_classes.egg-info/SOURCES.txt
ga_bi_distribution_classes.egg-info/dependency_links.txt
ga_bi_distribution_classes.egg-info/not-zip-safe
ga_bi_distribution_classes.egg-info/top_level.txt