Metadata-Version: 1.0
Name: ga-bi-distribution-classes
Version: 0.1
Summary: Gaussian and Binomial distribution classes
Home-page: UNKNOWN
Author: UNKNOWN
Author-email: UNKNOWN
License: UNKNOWN
Platform: UNKNOWN
